netcdf2csv/__init__.py
netcdf2csv/main.py
netcdf2csv-0.0.3.dist-info/LICENSE
netcdf2csv-0.0.3.dist-info/METADATA
netcdf2csv-0.0.3.dist-info/WHEEL
netcdf2csv-0.0.3.dist-info/top_level.txt
netcdf2csv-0.0.3.dist-info/RECORD
